{
    "general": {
        "_desc": "Enable Webinterface without going into AP Mode",
        "_memPos": "",
        "_fwVer": "3.0.8"
    },
    "positions": [{
        "_id": 0,
        "_name": "Prepare/CloseWifiConfigOnDoubleEar?",
        "_fwVer": "3.0.8",
        "offset": 0,
        "search":  ["38", "b5", "04", "46", "0d", "46", "ff", "f7", "1b", "fd"]
    }],
    "searchAndReplace": [{
        "_desc": "Keep in WiFi in ROLE_STA instead of switching to ROLE_AP",
        "_fwVer": "3.0.5+",
        "search":  [
            "13", "db", "00", "21", "02", "20"
        ],
        "replace": [
            "??", "??", "??", "??", "00", "??"
        ]
    },{
        "_desc": "Disable check on SlDrvCmd result",
        "_fwVer": "3.0.5+",
        "search":  [
            "00", "2b", "06", "db"
        ],
        "replace": [
            "??", "??", "00", "bf"
        ]
    },{
        "_desc": "Branch to tonie mode (instead of blue pulsing)",
        "_fwVer": "3.0.8",
        "search":  [
            "fb", "f7", "fa", "ff",
            "ab", "e5"
        ],
        "replace": [
            "??", "??", "??", "??",
            "06", "e0"
        ]
    }]
}
